git_trunk/__init__.py
git_trunk/git_trunk_base.py
git_trunk/git_trunk_commands.py
git_trunk/git_trunk_config.py
git_trunk/tests/__init__.py
git_trunk/tests/common.py
git_trunk/tests/test_git_trunk_finish.py
git_trunk/tests/test_git_trunk_init.py
git_trunk/tests/test_git_trunk_refresh.py
git_trunk/tests/test_git_trunk_release.py
git_trunk/tests/test_git_trunk_squash.py
git_trunk/tests/test_git_trunk_start.py
git_trunk/tests/test_git_trunk_submodule_update.py
git_trunk-0.7.1.data/scripts/git-trunk
git_trunk-0.7.1.dist-info/LICENSE
git_trunk-0.7.1.dist-info/METADATA
git_trunk-0.7.1.dist-info/WHEEL
git_trunk-0.7.1.dist-info/top_level.txt
git_trunk-0.7.1.dist-info/RECORD
