Metadata-Version: 2.1
Name: git_trunk
Version: 0.7.1
Summary: Git Trunk based workflow
Home-page: https://github.com/focusate/git-trunk
Maintainer: Andrius Laukavičius
Maintainer-email: andrius@timefordev.com
License: LGPLv3
Classifier: Environment :: Other Environment
Classifier: Intended Audience :: Developers
Classifier: Programming Language :: Python :: 3.8
Classifier: Programming Language :: Python :: 3.9
Classifier: Programming Language :: Python :: 3.10
Classifier: Programming Language :: Python :: 3.11
Classifier: Programming Language :: Python :: 3.12
Classifier: Topic :: Software Development
Classifier: Topic :: Utilities
Requires-Python: >=3.8
License-File: LICENSE
Requires-Dist: footil >=0.24.0
Requires-Dist: gitpython
Provides-Extra: test
Requires-Dist: pytest ; extra == 'test'
